LICENSE.txt
MANIFEST.in
README.md
requirements.txt
setup.py
djangorestframework_saasy.egg-info/PKG-INFO
djangorestframework_saasy.egg-info/SOURCES.txt
djangorestframework_saasy.egg-info/dependency_links.txt
djangorestframework_saasy.egg-info/requires.txt
djangorestframework_saasy.egg-info/top_level.txt
rest_framework_saasy/__init__.py
rest_framework_saasy/client.py
rest_framework_saasy/routers.py
rest_framework_saasy/settings.py
rest_framework_saasy/viewsets.py
rest_framework_saasy/runtests/__init__.py
rest_framework_saasy/runtests/runtests.py
rest_framework_saasy/runtests/settings.py
rest_framework_saasy/runtests/urls.py
rest_framework_saasy/tests/__init__.py
rest_framework_saasy/tests/models.py
rest_framework_saasy/tests/test_routers.py
rest_framework_saasy/tests/foo_bar-123/__init__.py
rest_framework_saasy/tests/foo_bar-123/test_routers.py