Metadata-Version: 1.0
Name: djangorestframework-saasy
Version: 0.1
Summary: SaaS plugin for the django rest framework
Home-page: https://github.com/juannyg/django-rest-framework-saasy
Author: Juan Gutierrez
Author-email: UNKNOWN
License: MIT
Platform: UNKNOWN
